rinjani/__init__.py
rinjani-1.0.3.dist-info/METADATA
rinjani-1.0.3.dist-info/WHEEL
rinjani-1.0.3.dist-info/top_level.txt
rinjani-1.0.3.dist-info/RECORD
